pykasm/__init__.py
pykasm/_bin.py
pykasm/utils.py
pykasm/CLib/pyasm.cpp
pykasm/__pycache__/__init__.cpython-312.pyc
pykasm/__pycache__/__init__.cpython-313.pyc
pykasm/__pycache__/_bin.cpython-312.pyc
pykasm/__pycache__/make_env.cpython-312.pyc
pykasm/__pycache__/utils.cpython-312.pyc
pykasm/__pycache__/utils.cpython-313.pyc
pykasm/lib/amd64pyasm.so
pykasm/lib/arm64pyasm.so
pykasm/lib/libpyasm.a
pykasm/lib/pyasm.dll
pykasm/rasm/keystone/lbuild/llvm/lib/libamd64keystone.so.0
pykasm/rasm/keystone/lbuild/llvm/lib/libarm64keystone.so.0
pykasm/rasm/keystone/winbuild/llvm/lib/keystone.dll
pykasm/rasm/keystone/winbuild/llvm/lib/keystone.exp
pykasm/rasm/keystone/winbuild/llvm/lib/keystone.lib
pykasm/rasm/lib/libamd64rasm.so
pykasm/rasm/lib/libarm64rasm.so
pykasm/rasm/lib/librasm.a
pykasm/rasm/lib/rasm.dll
pykasm-0.2.3.dist-info/METADATA
pykasm-0.2.3.dist-info/WHEEL
pykasm-0.2.3.dist-info/top_level.txt
pykasm-0.2.3.dist-info/RECORD
