Metadata-Version: 2.4
Name: pykasm
Version: 0.2.3
Summary: A library for low-level abstract use to high-level.
Author-email: Jhonata Rios Carneiro <jhonatacarneirorios432@gmail.com>
Project-URL: Homepage, https://github.com/Jhonataplayyt/pykasm
Project-URL: Repository, https://github.com/Jhonataplayyt/pykasm
Classifier: Programming Language :: Python :: 3
Classifier: Operating System :: OS Independent
Requires-Python: >=3.8
